magicwand/__init__.py
magicwand/bin/magicwand
magicwand/magicwand_cli/__init__.py
magicwand/magicwand_cli/cli.py
magicwand/magicwand_cli/tests/__init__.py
magicwand/magicwand_cli/tests/test_cli.py
magicwand/magicwand_commands/__init__.py
magicwand/magicwand_components/__init__.py
magicwand/magicwand_components/mw_calibrate.py
magicwand/magicwand_components/mw_component.py
magicwand/magicwand_components/mw_runner.py
magicwand/magicwand_components/attacks/__init__.py
magicwand/magicwand_components/attacks/apachekill/__init__.py
magicwand/magicwand_components/attacks/apachekill/apachekill.json
magicwand/magicwand_components/attacks/apachekill/apachekill.py
magicwand/magicwand_components/attacks/apachekill/apachekill.yml
magicwand/magicwand_components/attacks/goloris/__init__.py
magicwand/magicwand_components/attacks/goloris/goloris.json
magicwand/magicwand_components/attacks/goloris/goloris.py
magicwand/magicwand_components/attacks/goloris/goloris.yml
magicwand/magicwand_components/attacks/httpflood/__init__.py
magicwand/magicwand_components/attacks/httpflood/httpflood.json
magicwand/magicwand_components/attacks/httpflood/httpflood.py
magicwand/magicwand_components/attacks/httpflood/httpflood.yml
magicwand/magicwand_components/attacks/sht_rudeadyet/__init__.py
magicwand/magicwand_components/attacks/sht_rudeadyet/sht_rudeadyet.json
magicwand/magicwand_components/attacks/sht_rudeadyet/sht_rudeadyet.py
magicwand/magicwand_components/attacks/sht_rudeadyet/sht_rudeadyet.yml
magicwand/magicwand_components/attacks/sht_slowloris/__init__.py
magicwand/magicwand_components/attacks/sht_slowloris/sht_slowloris.json
magicwand/magicwand_components/attacks/sht_slowloris/sht_slowloris.py
magicwand/magicwand_components/attacks/sht_slowloris/sht_slowloris.yml
magicwand/magicwand_components/attacks/sht_slowread/__init__.py
magicwand/magicwand_components/attacks/sht_slowread/sht_slowread.json
magicwand/magicwand_components/attacks/sht_slowread/sht_slowread.py
magicwand-1.0.3.dist-info/LICENSE
magicwand-1.0.3.dist-info/METADATA
magicwand-1.0.3.dist-info/WHEEL
magicwand-1.0.3.dist-info/top_level.txt
magicwand-1.0.3.dist-info/RECORD
