Metadata-Version: 2.1
Name: magicwand
Version: 1.0.3
Summary: The Magicwand Data Tool is a platform generate TCP traffic data for identifying differences between normal TCP traffic and malicious 'low volume' denial of service traffic.
Home-page: https://github.com/twosixlabs/magicwand-datatool
Author: Two Six Labs
Author-email: magicwand@twosixlabs.com
License: UNKNOWN
Keywords: python,MAGICWAND,TCP,DDOS,locust
Platform: UNKNOWN
Classifier: Development Status :: 5 - Production/Stable
Classifier: Intended Audience :: Developers
Classifier: Natural Language :: English
Classifier: Programming Language :: Python
Classifier: Programming Language :: Python :: 3
Classifier: Programming Language :: Python :: 3.6
Classifier: Programming Language :: Python :: 3.7
Classifier: Programming Language :: Python :: 3.8
Requires-Python: >3.6
Requires-Dist: botocore (==1.17.48)
Requires-Dist: boto3 (==1.14.48)
Requires-Dist: Click (==7.0)
Requires-Dist: pandas (==1.1.1)
Requires-Dist: altair (==4.1.0)
Requires-Dist: jinja2 (==2.10.1)
Requires-Dist: numpy (==1.18.1)
